bibquery/__init__.py
bibquery/bibquery.py
bibquery/utils.py
bibquery/res/bibitnow_patched.xpi
bibquery/res/urlSpecificAdjusterList.json
bibquery/res/prefselectors/aachen.js
bibquery/res/prefselectors/aap.js
bibquery/res/prefselectors/acm.js
bibquery/res/prefselectors/acs.js
bibquery/res/prefselectors/agris.js
bibquery/res/prefselectors/aip.js
bibquery/res/prefselectors/ajas.js
bibquery/res/prefselectors/amazon.js
bibquery/res/prefselectors/annualreviews.js
bibquery/res/prefselectors/aps.js
bibquery/res/prefselectors/arxiv.js
bibquery/res/prefselectors/ascopubs.js
bibquery/res/prefselectors/bbc.js
bibquery/res/prefselectors/bioone.js
bibquery/res/prefselectors/biorxiv.js
bibquery/res/prefselectors/bmj.js
bibquery/res/prefselectors/bookdepository.js
bibquery/res/prefselectors/cpl.js
bibquery/res/prefselectors/csh.js
bibquery/res/prefselectors/darwiniana.js
bibquery/res/prefselectors/degruyter.js
bibquery/res/prefselectors/elsevier-book.js
bibquery/res/prefselectors/genialokal.js
bibquery/res/prefselectors/github.js
bibquery/res/prefselectors/goodreads.js
bibquery/res/prefselectors/google-book.js
bibquery/res/prefselectors/heise.js
bibquery/res/prefselectors/hindawi.js
bibquery/res/prefselectors/ieee.js
bibquery/res/prefselectors/ingentaconnect.js
bibquery/res/prefselectors/iop.js
bibquery/res/prefselectors/jeulan.js
bibquery/res/prefselectors/jps.js
bibquery/res/prefselectors/jstor.js
bibquery/res/prefselectors/liebert.js
bibquery/res/prefselectors/lww.js
bibquery/res/prefselectors/mdpi.js
bibquery/res/prefselectors/nature.js
bibquery/res/prefselectors/ncbi-book.js
bibquery/res/prefselectors/nejm.js
bibquery/res/prefselectors/nytimes.js
bibquery/res/prefselectors/oreilly.js
bibquery/res/prefselectors/osa.js
bibquery/res/prefselectors/oup-journals.js
bibquery/res/prefselectors/oup.js
bibquery/res/prefselectors/oxford-archive.js
bibquery/res/prefselectors/pmc.js
bibquery/res/prefselectors/pnas.js
bibquery/res/prefselectors/princeton.js
bibquery-1.2.4.dist-info/LICENSE
bibquery-1.2.4.dist-info/METADATA
bibquery-1.2.4.dist-info/WHEEL
bibquery-1.2.4.dist-info/top_level.txt
bibquery-1.2.4.dist-info/RECORD
