Metadata-Version: 2.1
Name: bibquery
Version: 1.2.4
Summary: Creates BibTeX entries from links using BibItNow (https://github.com/Langenscheiss/bibitnow), Google Scholar and Selenium.
Home-page: https://github.com/TimSchneider42/python-bibquery
Author: Tim Schneider
Author-email: tim@robot-learning.de
License-File: LICENSE
Requires-Dist: selenium (==4.7.2)
Requires-Dist: webdriver-manager (==3.8.5)
